PHJF/__init__.py
PHJF/data.py
PHJF/open_web.py
PHJF-0.0.6.1.dist-info/LICENSE
PHJF-0.0.6.1.dist-info/METADATA
PHJF-0.0.6.1.dist-info/WHEEL
PHJF-0.0.6.1.dist-info/top_level.txt
PHJF-0.0.6.1.dist-info/RECORD
