Metadata-Version: 2.1
Name: PHJF
Version: 0.0.6.1
Summary: 使用python将html转化成json并部署到服务器
Home-page: https://github.com/Xuanluo-Qiu/PHJF
Author: CCAil
Author-email: vioercer@otlook.com
License: UNKNOWN
Platform: UNKNOWN
Classifier: Programming Language :: Python :: 3
Classifier: License :: OSI Approved :: MIT License
Classifier: Operating System :: OS Independent
